query_table/__init__.py
query_table/__main__.py
query_table/_version.py
query_table/enums.py
query_table/server.py
query_table/tool.py
query_table/sites/__init__.py
query_table/sites/eastmoney.py
query_table/sites/iwencai.py
query_table/sites/tdx.py
query_table-0.2.5.dist-info/licenses/LICENSE
query_table-0.2.5.dist-info/METADATA
query_table-0.2.5.dist-info/WHEEL
query_table-0.2.5.dist-info/top_level.txt
query_table-0.2.5.dist-info/RECORD
