Metadata-Version: 2.4
Name: query_table
Version: 0.2.5
Summary: query table from website, support MCP
Author-email: wukan <wu-kan@163.com>
License: MIT License
Keywords: playwright,mcp,table,iwencai,tdx,eastmoney
Classifier: Development Status :: 4 - Beta
Classifier: Programming Language :: Python
Requires-Python: >=3.10
License-File: LICENSE
Requires-Dist: pandas
Requires-Dist: loguru
Requires-Dist: playwright
Requires-Dist: mcp
Dynamic: license-file
